MANIFEST.in
README.md
setup.py
salesforce_lambda/__init__.py
salesforce_lambda.egg-info/PKG-INFO
salesforce_lambda.egg-info/SOURCES.txt
salesforce_lambda.egg-info/dependency_links.txt
salesforce_lambda.egg-info/not-zip-safe
salesforce_lambda.egg-info/requires.txt
salesforce_lambda.egg-info/top_level.txt