Metadata-Version: 1.1
Name: salesforce-lambda
Version: 0.1
Summary: Fill me in
Home-page: https://github.com/iamjohnnym/salesforce-lambda.git
Author: John Martin
Author-email: john.martin@configure.systems
License: MIT
Keywords: some string of keywords
Platform: UNKNOWN
Classifier: Development Status :: 3 - Alpha
Classifier: License :: OSI Approved :: MIT License
Classifier: Programming Language :: Python :: 2.7
Classifier: Topic :: Text Processing :: Linguistic
